{
  "postgres": {
    "client": "pg",
    "connection": "DATABASE_URL"
  },
  "authentication": {
    "secret": "SECRET_TOKEN",
    "jwtOptions": {
      "audience": "AUDIENCE_CLAIM"
    }
  },
  "mailer": {
    "nodemailerOptions": {
      "message": {
        "from": "SENDER_EMAIL",
        "replyTo": "REPLY_TO_EMAIL"
      },
      "send": true,
      "preview": false
    },
    "etherealTransport": {
      "host": "smtp.ethereal.email",
      "port": 587,
      "secure": false,
      "auth": {
        "user": "ETHEREAL_EMAIL",
        "pass": "ETHEREAL_PASSWORD"
      }
    },
    "postmarkTransport": {
      "auth": {
        "apiKey": "POSTMARK_API_KEY"
      }
    },
    "postmarkSandboxTransport": {
      "auth": {
        "apiKey": "POSTMARK_SANDBOX_API_KEY"
      }
    },
    "transport": "EMAIL_TRANSPORT",
    "auditRecipients": "AUDIT_RECIPIENTS"
  },
  "errorhandler": {},
  "enableJobScheduler": true,
  "corsOrigins": "CORS_ORIGINS"
}
